[{"time": 11.78, "text": "Everyone's so soft, everyone's so sensitive", "words": [{"word": "Everyone's", "start": 11.78, "end": 12.38}, {"word": "so", "start": 12.38, "end": 12.88}, {"word": "soft,", "start": 12.98, "end": 13.14}, {"word": "everyone's", "start": 13.14, "end": 13.58}, {"word": "so", "start": 13.58, "end": 14}, {"word": "sensitive", "start": 14, "end": 15.74, "stretch": true}]}, {"time": 16.1, "text": "Do I offend you? You're hanging on my sentences", "words": [{"word": "Do", "start": 16.1, "end": 16.38}, {"word": "I", "start": 16.38, "end": 16.66}, {"word": "offend", "start": 16.66, "end": 17.04}, {"word": "you?", "start": 17.18, "end": 17.28}, {"word": "You're", "start": 17.28, "end": 17.58}, {"word": "hanging", "start": 17.58, "end": 17.88}, {"word": "on", "start": 17.88, "end": 18.02}, {"word": "my", "start": 18.02, "end": 18.52}, {"word": "sentences", "start": 18.6, "end": 18.94}]}, {"time": 18.99, "text": "You can keep your costume and you can keep your mask", "words": [{"word": "You", "start": 18.99, "end": 19.45}, {"word": "can", "start": 19.45, "end": 19.65}, {"word": "keep", "start": 19.65, "end": 19.87}, {"word": "your", "start": 19.87, "end": 20.17}, {"word": "costume", "start": 20.17, "end": 20.67}, {"word": "and", "start": 20.67, "end": 20.91}, {"word": "you", "start": 20.91, "end": 21.03}, {"word": "can", "start": 21.03, "end": 21.31}, {"word": "keep", "start": 21.31, "end": 21.53}, {"word": "your", "start": 21.53, "end": 21.91}, {"word": "mask", "start": 21.91, "end": 22.52, "stretch": true}]}, {"time": 22.58, "text": "I'ma take a bow so you can kiss my ass", "words": [{"word": "I'ma", "start": 22.58, "end": 22.8}, {"word": "take", "start": 22.8, "end": 23}, {"word": "a", "start": 23, "end": 23.22}, {"word": "bow", "start": 23.22, "end": 23.52}, {"word": "so", "start": 23.52, "end": 23.84}, {"word": "you", "start": 23.84, "end": 24.1}, {"word": "can", "start": 24.1, "end": 24.48}, {"word": "kiss", "start": 24.48, "end": 24.86}, {"word": "my", "start": 24.86, "end": 25.06}, {"word": "ass", "start": 25.06, "end": 25.27, "stretch": true}]}, {"time": 25.32, "text": "I never signed up for your drama", "words": [{"word": "I", "start": 25.32, "end": 25.52}, {"word": "never", "start": 25.52, "end": 25.8}, {"word": "signed", "start": 25.8, "end": 26.18}, {"word": "up", "start": 26.18, "end": 26.6}, {"word": "for", "start": 26.6, "end": 26.96}, {"word": "your", "start": 26.96, "end": 27.22}, {"word": "drama", "start": 27.22, "end": 28.197, "stretch": true}]}, {"time": 28.247, "text": "Up for your drama, up for your drama club", "words": [{"word": "Up", "start": 28.247, "end": 28.727}, {"word": "for", "start": 28.727, "end": 29.027}, {"word": "your", "start": 29.027, "end": 29.247}, {"word": "drama,", "start": 29.247, "end": 29.747}, {"word": "up", "start": 30.127, "end": 30.407}, {"word": "for", "start": 30.407, "end": 30.647}, {"word": "your", "start": 30.647, "end": 30.947}, {"word": "drama", "start": 30.947, "end": 31.327}, {"word": "club", "start": 31.327, "end": 32.237, "stretch": true}]}, {"time": 32.287, "text": "I never signed up for your drama", "words": [{"word": "I", "start": 32.287, "end": 32.787}, {"word": "never", "start": 32.867, "end": 33.287}, {"word": "signed", "start": 33.287, "end": 33.687}, {"word": "up", "start": 33.687, "end": 34.087}, {"word": "for", "start": 34.087, "end": 34.307}, {"word": "your", "start": 34.307, "end": 34.567}, {"word": "drama", "start": 34.567, "end": 35.407, "stretch": true}]}, {"time": 35.457, "text": "Up for your drama club", "words": [{"word": "Up", "start": 35.457, "end": 35.737}, {"word": "for", "start": 35.737, "end": 35.937}, {"word": "your", "start": 35.937, "end": 36.117}, {"word": "drama", "start": 36.117, "end": 36.537}, {"word": "club", "start": 36.537, "end": 38.137, "stretch": true}]}, {"time": 38.187, "text": "They try to feed you lines that you have to memorize", "words": [{"word": "They", "start": 38.187, "end": 38.747}, {"word": "try", "start": 38.747, "end": 38.947}, {"word": "to", "start": 38.947, "end": 39.207}, {"word": "feed", "start": 39.207, "end": 39.347}, {"word": "you", "start": 39.347, "end": 39.567}, {"word": "lines", "start": 39.567, "end": 39.867}, {"word": "that", "start": 39.867, "end": 40.067}, {"word": "you", "start": 40.067, "end": 40.247}, {"word": "have", "start": 40.247, "end": 40.467}, {"word": "to", "start": 40.467, "end": 40.767}, {"word": "memorize", "start": 40.767, "end": 41.707, "stretch": true}]}, {"time": 41.757, "text": "You always hide behind your Wizard of Oz disguise", "words": [{"word": "You", "start": 41.757, "end": 42.197}, {"word": "always", "start": 42.197, "end": 42.577}, {"word": "hide", "start": 42.577, "end": 42.817}, {"word": "behind", "start": 42.817, "end": 43.457}, {"word": "your", "start": 43.457, "end": 43.817}, {"word": "Wizard", "start": 43.817, "end": 44.077}, {"word": "of", "start": 44.077, "end": 44.377}, {"word": "Oz", "start": 44.377, "end": 44.557}, {"word": "disguise", "start": 44.557, "end": 45.087, "stretch": true}]}, {"time": 45.137, "text": "Do you even have a brain? You're sticking to a page", "words": [{"word": "Do", "start": 45.137, "end": 45.397}, {"word": "you", "start": 45.397, "end": 45.557}, {"word": "even", "start": 45.557, "end": 46.017}, {"word": "have", "start": 46.017, "end": 46.277}, {"word": "a", "start": 46.277, "end": 46.517}, {"word": "brain?", "start": 46.517, "end": 46.717}, {"word": "You're", "start": 46.937, "end": 47.177}, {"word": "sticking", "start": 47.177, "end": 47.497}, {"word": "to", "start": 47.497, "end": 47.917}, {"word": "a", "start": 47.917, "end": 48.157}, {"word": "page", "start": 48.157, "end": 48.607, "stretch": true}]}, {"time": 48.657, "text": "You're faking all your pain, yeah, you're bleeding on a stage", "words": [{"word": "You're", "start": 48.657, "end": 48.937}, {"word": "faking", "start": 48.937, "end": 49.357}, {"word": "all", "start": 49.357, "end": 49.737}, {"word": "your", "start": 49.737, "end": 49.977}, {"word": "pain,", "start": 49.977, "end": 50.237}, {"word": "yeah,", "start": 50.237, "end": 50.517}, {"word": "you're", "start": 50.637, "end": 50.737}, {"word": "bleeding", "start": 50.737, "end": 50.957}, {"word": "on", "start": 50.957, "end": 51.337}, {"word": "a", "start": 51.337, "end": 51.677}, {"word": "stage", "start": 51.677, "end": 52.306, "stretch": true}]}, {"time": 52.356, "text": "I never signed up for your drama", "words": [{"word": "I", "start": 52.356, "end": 52.576}, {"word": "never", "start": 52.576, "end": 52.956}, {"word": "signed", "start": 52.956, "end": 53.396}, {"word": "up", "start": 53.396, "end": 53.816}, {"word": "for", "start": 53.816, "end": 54.216}, {"word": "your", "start": 54.216, "end": 54.456}, {"word": "drama", "start": 54.456, "end": 55.514, "stretch": true}]}, {"time": 55.564, "text": "Up for your drama, up for your drama club", "words": [{"word": "Up", "start": 55.564, "end": 56.064}, {"word": "for", "start": 56.104, "end": 56.444}, {"word": "your", "start": 56.444, "end": 56.624}, {"word": "drama,", "start": 56.624, "end": 57.184}, {"word": "up", "start": 57.564, "end": 57.764}, {"word": "for", "start": 57.764, "end": 58.064}, {"word": "your", "start": 58.064, "end": 58.344}, {"word": "drama", "start": 58.344, "end": 58.704}, {"word": "club", "start": 58.704, "end": 59.647, "stretch": true}]}, {"time": 59.697, "text": "I never signed up for your drama", "words": [{"word": "I", "start": 59.697, "end": 60.077}, {"word": "never", "start": 60.077, "end": 60.517}, {"word": "signed", "start": 60.517, "end": 60.897}, {"word": "up", "start": 60.897, "end": 61.317}, {"word": "for", "start": 61.317, "end": 61.537}, {"word": "your", "start": 61.537, "end": 61.777}, {"word": "drama", "start": 61.777, "end": 62.497, "stretch": true}]}, {"time": 62.547, "text": "Up for your drama club (Ooh)", "words": [{"word": "Up", "start": 62.547, "end": 62.767}, {"word": "for", "start": 62.767, "end": 63.027}, {"word": "your", "start": 63.027, "end": 63.287}, {"word": "drama", "start": 63.287, "end": 63.627}, {"word": "club", "start": 63.627, "end": 64.147}, {"word": "(Ooh)", "start": 64.147, "end": 66.147, "stretch": true}]}, {"time": 66.197, "text": "I never signed up for your drama club (Ooh)", "words": [{"word": "I", "start": 66.197, "end": 66.637}, {"word": "never", "start": 66.637, "end": 67.137}, {"word": "signed", "start": 67.137, "end": 67.577}, {"word": "up", "start": 67.577, "end": 67.757}, {"word": "for", "start": 67.757, "end": 67.997}, {"word": "your", "start": 67.997, "end": 68.337}, {"word": "drama", "start": 68.337, "end": 69.037}, {"word": "club", "start": 69.037, "end": 70.297}, {"word": "(Ooh)", "start": 70.297, "end": 71.994, "stretch": true}]}, {"time": 72.044, "text": "For your drama club", "words": [{"word": "For", "start": 72.044, "end": 72.524}, {"word": "your", "start": 72.524, "end": 72.804}, {"word": "drama", "start": 72.804, "end": 73.144}, {"word": "club", "start": 73.144, "end": 74.164, "stretch": true}]}, {"time": 74.214, "text": "I never signed up for your drama (Ooh)", "words": [{"word": "I", "start": 74.214, "end": 74.594}, {"word": "never", "start": 74.594, "end": 75.054}, {"word": "signed", "start": 75.054, "end": 75.494}, {"word": "up", "start": 75.494, "end": 75.674}, {"word": "for", "start": 75.674, "end": 75.994}, {"word": "your", "start": 75.994, "end": 76.474}, {"word": "drama", "start": 76.834, "end": 76.974}, {"word": "(Ooh)", "start": 76.974, "end": 77.074}]}, {"time": 77.124, "text": "Up for your drama, up for your drama club", "words": [{"word": "Up", "start": 77.124, "end": 77.264}, {"word": "for", "start": 77.264, "end": 77.564}, {"word": "your", "start": 77.564, "end": 77.764}, {"word": "drama,", "start": 77.764, "end": 78.344}, {"word": "up", "start": 78.724, "end": 78.904}, {"word": "for", "start": 78.904, "end": 79.184}, {"word": "your", "start": 79.184, "end": 79.444}, {"word": "drama", "start": 79.444, "end": 79.804}, {"word": "club", "start": 79.804, "end": 80.749, "stretch": true}]}, {"time": 80.86, "text": "I never signed up for your drama (Ooh)", "words": [{"word": "I", "start": 80.86, "end": 80.918}, {"word": "never", "start": 80.928, "end": 81.32}, {"word": "signed", "start": 81.32, "end": 81.9}, {"word": "up", "start": 81.9, "end": 82.04}, {"word": "for", "start": 82.04, "end": 82.105}, {"word": "your", "start": 82.115, "end": 82.3}, {"word": "drama", "start": 82.3, "end": 82.82}, {"word": "(Ooh)", "start": 82.82, "end": 82.92}]}, {"time": 82.97, "text": "Up for your drama, up for your drama club", "words": [{"word": "Up", "start": 82.97, "end": 83.45}, {"word": "for", "start": 83.61, "end": 83.71}, {"word": "your", "start": 83.71, "end": 84.01}, {"word": "drama,", "start": 84.01, "end": 84.51}, {"word": "up", "start": 84.83, "end": 85.07}, {"word": "for", "start": 85.23, "end": 85.35}, {"word": "your", "start": 85.35, "end": 85.67}, {"word": "drama", "start": 85.67, "end": 86.05}, {"word": "club", "start": 86.05, "end": 86.59, "stretch": true}]}, {"time": 86.64, "text": "I don't wanna be an actress, living by a script", "words": [{"word": "I", "start": 86.64, "end": 87.04}, {"word": "don't", "start": 87.04, "end": 87.3}, {"word": "wanna", "start": 87.3, "end": 87.62}, {"word": "be", "start": 87.62, "end": 88.04}, {"word": "an", "start": 88.04, "end": 88.34}, {"word": "actress,", "start": 88.34, "end": 89.56}, {"word": "living", "start": 90.72, "end": 90.86}, {"word": "by", "start": 90.86, "end": 91.26}, {"word": "a", "start": 91.26, "end": 91.6}, {"word": "script", "start": 91.6, "end": 93.43, "stretch": true}]}, {"time": 93.48, "text": "Who cares about practice? Hmm, I don't give a shit", "words": [{"word": "Who", "start": 93.48, "end": 93.51}, {"word": "cares", "start": 93.52, "end": 93.78}, {"word": "about", "start": 93.78, "end": 94.24}, {"word": "practice?", "start": 94.24, "end": 96.76}, {"word": "Hmm,", "start": 96.76, "end": 96.86}, {"word": "I", "start": 96.87, "end": 97.16}, {"word": "don't", "start": 97.16, "end": 97.42}, {"word": "give", "start": 97.42, "end": 97.8}, {"word": "a", "start": 97.8, "end": 98.3}, {"word": "shit", "start": 99.92, "end": 100.02}]}, {"time": 100.07, "text": "You're over-analyzing every word I say", "words": [{"word": "You're", "start": 100.07, "end": 100.79}, {"word": "over-analyzing", "start": 100.79, "end": 101.51}, {"word": "every", "start": 101.51, "end": 102.05}, {"word": "word", "start": 102.05, "end": 102.27}, {"word": "I", "start": 102.27, "end": 102.61}, {"word": "say", "start": 102.61, "end": 102.9}]}, {"time": 102.95, "text": "There's a whole world out there, you're living a play", "words": [{"word": "There's", "start": 102.95, "end": 103.25}, {"word": "a", "start": 103.25, "end": 103.61}, {"word": "whole", "start": 103.61, "end": 103.81}, {"word": "world", "start": 103.81, "end": 104.13}, {"word": "out", "start": 104.13, "end": 104.31}, {"word": "there,", "start": 104.31, "end": 104.85}, {"word": "you're", "start": 104.85, "end": 105.23}, {"word": "living", "start": 105.23, "end": 105.61}, {"word": "a", "start": 105.61, "end": 105.85}, {"word": "play", "start": 105.85, "end": 106.506, "stretch": true}]}, {"time": 106.556, "text": "Fuck your auditorium, I think it's pretty boring and", "words": [{"word": "Fuck", "start": 106.556, "end": 107.056}, {"word": "your", "start": 107.056, "end": 107.396}, {"word": "auditorium,", "start": 107.396, "end": 108.176}, {"word": "I", "start": 108.176, "end": 108.416}, {"word": "think", "start": 108.416, "end": 108.576}, {"word": "it's", "start": 108.576, "end": 108.816}, {"word": "pretty", "start": 108.816, "end": 109.116}, {"word": "boring", "start": 109.116, "end": 109.576}, {"word": "and", "start": 109.576, "end": 109.876}]}, {"time": 109.926, "text": "I never signed up for your drama", "words": [{"word": "I", "start": 109.926, "end": 110.366}, {"word": "never", "start": 110.366, "end": 110.786}, {"word": "signed", "start": 110.786, "end": 111.186}, {"word": "up", "start": 111.186, "end": 111.646}, {"word": "for", "start": 111.646, "end": 111.826}, {"word": "your", "start": 111.826, "end": 112.126}, {"word": "drama", "start": 112.126, "end": 112.796, "stretch": true}]}, {"time": 112.846, "text": "Up for your drama, up for your drama club", "words": [{"word": "Up", "start": 112.846, "end": 112.89}, {"word": "for", "start": 112.9, "end": 113.246}, {"word": "your", "start": 113.246, "end": 113.28}, {"word": "drama,", "start": 113.29, "end": 113.486}, {"word": "up", "start": 113.486, "end": 113.534}, {"word": "for", "start": 113.544, "end": 113.726}, {"word": "your", "start": 113.726, "end": 113.886}, {"word": "drama", "start": 113.896, "end": 114.206}, {"word": "club", "start": 114.206, "end": 114.786}]}, {"time": 116.15, "text": "I never signed up for your drama", "words": [{"word": "I", "start": 116.15, "end": 116.276}, {"word": "never", "start": 116.286, "end": 116.297}, {"word": "signed", "start": 116.307, "end": 116.326}, {"word": "up", "start": 116.336, "end": 116.836}, {"word": "for", "start": 117.03, "end": 117.323}, {"word": "your", "start": 117.333, "end": 117.47}, {"word": "drama", "start": 117.48, "end": 117.91}]}, {"time": 118.56, "text": "Up for your drama club (Ooh)", "words": [{"word": "Up", "start": 118.56, "end": 118.707}, {"word": "for", "start": 118.717, "end": 119.44}, {"word": "your", "start": 119.44, "end": 119.76}, {"word": "drama", "start": 119.76, "end": 121.76}, {"word": "club", "start": 123.32, "end": 124.2}, {"word": "(Ooh)", "start": 124.2, "end": 124.3}]}, {"time": 124.35, "text": "I never signed up for your drama club (Ooh)", "words": [{"word": "I", "start": 124.35, "end": 124.79}, {"word": "never", "start": 124.79, "end": 125.23}, {"word": "signed", "start": 125.23, "end": 125.71}, {"word": "up", "start": 125.71, "end": 125.89}, {"word": "for", "start": 125.89, "end": 126.15}, {"word": "your", "start": 126.15, "end": 126.45}, {"word": "drama", "start": 126.45, "end": 127.35}, {"word": "club", "start": 127.35, "end": 128.07}, {"word": "(Ooh)", "start": 128.07, "end": 129.807}]}, {"time": 130.9, "text": "For your drama club", "words": [{"word": "For", "start": 130.9, "end": 131.16}, {"word": "your", "start": 131.16, "end": 131.84}, {"word": "drama", "start": 131.84, "end": 132.4}, {"word": "club", "start": 132.4, "end": 132.5}]}, {"time": 132.55, "text": "I never signed up for your drama (Ooh)", "words": [{"word": "I", "start": 132.55, "end": 133.05}, {"word": "never", "start": 133.11, "end": 133.49}, {"word": "signed", "start": 133.49, "end": 133.91}, {"word": "up", "start": 133.91, "end": 134.37}, {"word": "for", "start": 134.37, "end": 134.55}, {"word": "your", "start": 134.55, "end": 134.87}, {"word": "drama", "start": 134.87, "end": 135.41}, {"word": "(Ooh)", "start": 135.41, "end": 135.49}]}, {"time": 135.54, "text": "Up for your drama, up for your drama club", "words": [{"word": "Up", "start": 135.54, "end": 136.0}, {"word": "for", "start": 136.0, "end": 136.2}, {"word": "your", "start": 136.2, "end": 136.62}, {"word": "drama,", "start": 136.62, "end": 137.1}, {"word": "up", "start": 137.1, "end": 137.6}, {"word": "for", "start": 138.86, "end": 139.569}, {"word": "your", "start": 139.62, "end": 140.02}, {"word": "drama", "start": 140.02, "end": 140.12}, {"word": "club", "start": 140.13, "end": 140.23, "stretch": true}]}, {"time": 140.28, "text": "I never signed up for your drama (Ooh)", "words": [{"word": "I", "start": 140.28, "end": 140.68}, {"word": "never", "start": 140.68, "end": 140.78}, {"word": "signed", "start": 140.79, "end": 140.89}, {"word": "up", "start": 140.9, "end": 141.0}, {"word": "for", "start": 141.01, "end": 141.11}, {"word": "your", "start": 141.12, "end": 141.22}, {"word": "drama", "start": 141.23, "end": 141.33}, {"word": "(Ooh)", "start": 141.34, "end": 142.211, "stretch": true}]}, {"time": 142.261, "text": "Up for your drama, up for your drama club", "words": [{"word": "Up", "start": 142.261, "end": 142.881}, {"word": "for", "start": 142.881, "end": 143.501}, {"word": "your", "start": 143.501, "end": 144.001}, {"word": "drama,", "start": 144.001, "end": 144.601}, {"word": "up", "start": 144.601, "end": 145.061}, {"word": "for", "start": 145.061, "end": 145.641}, {"word": "your", "start": 145.721, "end": 146.001}, {"word": "drama", "start": 146.001, "end": 146.101}, {"word": "club", "start": 146.111, "end": 147.711}]}, {"type": "vocal_cue", "time": 146.75, "end": 152.62}, {"time": 153.44, "text": "For your drama club", "words": [{"word": "For", "start": 153.44, "end": 153.58}, {"word": "your", "start": 153.59, "end": 154}, {"word": "drama", "start": 154, "end": 154.37}, {"word": "club", "start": 154.38, "end": 154.74}]}, {"type": "vocal_cue", "time": 155.04, "end": 166.14}, {"time": 157.73, "text": "Mmm, mmm"}, {"time": 166.44, "text": "I never signed up (Ooh), mmm, mmm", "words": [{"word": "I", "start": 166.44, "end": 166.8}, {"word": "never", "start": 166.8, "end": 167.3}, {"word": "signed", "start": 167.3, "end": 168}, {"word": "up", "start": 168, "end": 168.8}, {"word": "(Ooh),", "start": 169.82, "end": 171.38}, {"word": "mmm,", "start": 172, "end": 173.3}, {"word": "mmm", "start": 173.3, "end": 173.4}]}, {"time": 173.45, "text": "I never signed up (Ooh), never signed up", "words": [{"word": "I", "start": 173.45, "end": 173.525}, {"word": "never", "start": 173.535, "end": 174.05}, {"word": "signed", "start": 174.05, "end": 174.83}, {"word": "up", "start": 174.83, "end": 175.05}, {"word": "(Ooh),", "start": 175.05, "end": 175.63}, {"word": "never", "start": 175.63, "end": 176.17}, {"word": "signed", "start": 176.17, "end": 176.69}, {"word": "up", "start": 176.69, "end": 176.79}]}, {"time": 176.84, "text": "Never signed up for your drama club", "words": [{"word": "Never", "start": 176.84, "end": 177.36}, {"word": "signed", "start": 177.36, "end": 177.7}, {"word": "up", "start": 177.7, "end": 178.2}, {"word": "for", "start": 178.2, "end": 178.44}, {"word": "your", "start": 178.44, "end": 178.68}, {"word": "drama", "start": 178.68, "end": 179.04}, {"word": "club", "start": 179.04, "end": 179.892, "stretch": true}]}, {"time": 179.942, "text": "I never signed up for your drama (Ooh), for your drama", "words": [{"word": "I", "start": 179.942, "end": 180.442}, {"word": "never", "start": 180.762, "end": 181.262}, {"word": "signed", "start": 181.262, "end": 181.622}, {"word": "up", "start": 181.622, "end": 181.902}, {"word": "for", "start": 181.902, "end": 182.162}, {"word": "your", "start": 182.162, "end": 182.622}, {"word": "drama", "start": 182.622, "end": 183.422}, {"word": "(Ooh),", "start": 183.422, "end": 183.762}, {"word": "for", "start": 183.762, "end": 184.38}, {"word": "your", "start": 184.642, "end": 185.122}, {"word": "drama", "start": 185.122, "end": 185.222}]}, {"time": 185.272, "text": "For your drama club", "words": [{"word": "For", "start": 185.272, "end": 185.752}, {"word": "your", "start": 185.752, "end": 186.112}, {"word": "drama", "start": 186.112, "end": 186.512}, {"word": "club", "start": 186.512, "end": 187.642, "stretch": true}]}, {"time": 187.692, "text": "I never signed up for your drama (Ooh)", "words": [{"word": "I", "start": 187.692, "end": 187.757}, {"word": "never", "start": 187.767, "end": 188.212}, {"word": "signed", "start": 188.212, "end": 188.612}, {"word": "up", "start": 188.612, "end": 188.832}, {"word": "for", "start": 188.832, "end": 189.132}, {"word": "your", "start": 189.132, "end": 189.672}, {"word": "drama", "start": 189.672, "end": 190.192}, {"word": "(Ooh)", "start": 190.192, "end": 190.292}]}, {"time": 190.342, "text": "Up for your drama, for your drama club", "words": [{"word": "Up", "start": 190.342, "end": 190.842}, {"word": "for", "start": 190.862, "end": 191.162}, {"word": "your", "start": 191.162, "end": 191.482}, {"word": "drama,", "start": 191.482, "end": 191.982}, {"word": "for", "start": 192.482, "end": 192.742}, {"word": "your", "start": 192.742, "end": 193.102}, {"word": "drama", "start": 193.102, "end": 193.402}, {"word": "club", "start": 193.402, "end": 194.372, "stretch": true}]}, {"time": 194.422, "text": "I never signed up for your drama (Ooh)", "words": [{"word": "I", "start": 194.422, "end": 194.49}, {"word": "never", "start": 194.5, "end": 194.962}, {"word": "signed", "start": 194.962, "end": 195.022}, {"word": "up", "start": 195.032, "end": 195.322}, {"word": "for", "start": 195.322, "end": 195.427}, {"word": "your", "start": 195.437, "end": 195.742}, {"word": "drama", "start": 195.742, "end": 196.545}, {"word": "(Ooh)", "start": 196.845, "end": 197.302, "stretch": true}]}, {"time": 194.71, "text": "Up for your drama, up for your drama club"}, {"time": 198.62, "text": "I never signed up for your drama (Ooh)"}, {"time": 201.49, "text": "Up for your drama, up for your drama club", "words": [{"word": "Up", "start": 201.49, "end": 201.53}, {"word": "for", "start": 201.54, "end": 201.64}, {"word": "your", "start": 201.65, "end": 201.85}, {"word": "drama,", "start": 201.85, "end": 201.89}, {"word": "up", "start": 201.9, "end": 202.09}, {"word": "for", "start": 202.09, "end": 202.205}, {"word": "your", "start": 202.215, "end": 202.55}, {"word": "drama", "start": 202.55, "end": 202.74}, {"word": "club", "start": 202.75, "end": 202.93}]}, {"type": "vocal_cue", "time": 203.23, "end": 211.34}, {"type": "vocal_cue", "time": 203.23, "end": 214.01}, {"time": 205.27, "text": "I never signed up for your drama (Ooh)"}, {"time": 207.65, "text": "Up for your drama, up for your drama club"}, {"time": 211.64, "text": "I never signed up for your drama (Ooh)"}, {"time": 214.31, "text": "Up for your drama, up for your drama club"}]