[{"time":9.3,"text":"\"If","words":[{"word":"\"If","start":9.3,"end":10.79,"sung":true,"stretch":true}],"end":10.79},{"time":13.33,"text":"But you've got the music","words":[{"word":"But","start":13.33,"end":13.51,"spoken":true},{"word":"you've","start":13.52,"end":13.56},{"word":"got","start":13.57,"end":13.67,"spoken":true},{"word":"the","start":14.41,"end":14.79,"spoken":true},{"word":"music","start":14.8,"end":14.9,"spoken":true}],"end":14.9},{"time":23.16,"text":"Down on the West Coast, I get this feeling like","words":[{"word":"Down","start":23.16,"end":23.26},{"word":"on","start":23.27,"end":23.37},{"word":"the","start":23.38,"end":23.48,"spoken":true},{"word":"West","start":23.49,"end":23.59,"spoken":true},{"word":"Coast,","start":23.6,"end":23.7},{"word":"I","start":23.71,"end":23.81},{"word":"get","start":23.82,"end":23.92},{"word":"this","start":23.93,"end":24.03},{"word":"feeling","start":24.04,"end":24.14},{"word":"like","start":24.15,"end":24.25}],"end":24.25},{"time":27.79,"text":"It all could happen, that's why I'm leaving","words":[{"word":"It","start":27.79,"end":27.89,"whisper":true},{"word":"all","start":27.9,"end":28},{"word":"could","start":28.01,"end":28.11,"spoken":true},{"word":"happen,","start":28.12,"end":28.22,"spoken":true},{"word":"that's","start":28.23,"end":28.33,"spoken":true},{"word":"why","start":28.34,"end":28.44},{"word":"I'm","start":28.45,"end":28.55},{"word":"leaving","start":28.56,"end":28.66}],"end":28.66},{"time":29.67,"text":"you're not drinkin', then you're not playin'\"","words":[{"word":"you're","start":29.67,"end":30.19,"spoken":true},{"word":"not","start":30.29,"end":30.47},{"word":"drinkin',","start":30.48,"end":31.63,"spoken":true},{"word":"then","start":31.64,"end":31.95,"spoken":true},{"word":"you're","start":31.96,"end":32.11},{"word":"not","start":32.16,"end":32.31,"spoken":true},{"word":"playin'\"","start":32.36,"end":32.46,"spoken":true}],"end":32.46},{"time":31.88,"text":"You for the music,","words":[{"word":"You","start":31.88,"end":31.98,"spoken":true},{"word":"for","start":31.99,"end":32.09},{"word":"the","start":32.1,"end":32.2,"spoken":true},{"word":"music,","start":32.21,"end":32.31,"spoken":true}],"end":32.31},{"time":32.32,"text":"you for the music","words":[{"word":"you","start":32.32,"end":32.42,"spoken":true},{"word":"for","start":32.43,"end":32.53,"spoken":true},{"word":"the","start":32.54,"end":32.64},{"word":"music","start":32.65,"end":32.75}],"end":32.75},{"time":33.26,"text":"You've got the music","words":[{"word":"You've","start":33.26,"end":33.41,"spoken":true},{"word":"got","start":33.46,"end":33.61},{"word":"the","start":33.66,"end":33.96},{"word":"music","start":33.97,"end":35.46,"stretch":true}],"end":35.46},{"time":36.31,"text":"It's true, it's true","words":[{"word":"It's","start":36.31,"end":36.41},{"word":"true,","start":36.42,"end":36.52,"spoken":true},{"word":"it's","start":36.53,"end":36.63},{"word":"true","start":36.64,"end":36.74,"spoken":true}],"end":36.74},{"time":39.74,"text":"in you, don't you?","words":[{"word":"in","start":39.74,"end":40},{"word":"you,","start":40.1,"end":41.02,"spoken":true},{"word":"don't","start":41.03,"end":41.13},{"word":"you?","start":41.14,"end":41.24}],"end":41.24},{"time":40.69,"text":"I push it hard, you pull away, I'm feelin' hotter than fire","words":[{"word":"I","start":40.69,"end":40.79,"whisper":true},{"word":"push","start":40.8,"end":40.9,"whisper":true},{"word":"it","start":40.91,"end":41.01},{"word":"hard,","start":41.02,"end":41.12},{"word":"you","start":41.13,"end":41.23},{"word":"pull","start":41.24,"end":41.34},{"word":"away,","start":41.35,"end":41.45},{"word":"I'm","start":41.46,"end":41.56},{"word":"feelin'","start":41.57,"end":41.67},{"word":"hotter","start":41.68,"end":41.78},{"word":"than","start":41.79,"end":41.89,"spoken":true},{"word":"fire","start":41.9,"end":42,"spoken":true}],"end":42},{"time":45.24,"text":"I'm feeling like there's no one else, brings me higher and higher","words":[{"word":"I'm","start":45.24,"end":45.34,"spoken":true},{"word":"feeling","start":45.35,"end":45.45,"spoken":true},{"word":"like","start":45.46,"end":45.56,"spoken":true},{"word":"there's","start":45.57,"end":45.67,"spoken":true},{"word":"no","start":45.68,"end":45.78,"spoken":true},{"word":"one","start":45.79,"end":45.89},{"word":"else,","start":45.9,"end":46,"spoken":true},{"word":"brings","start":46.01,"end":46.11,"spoken":true},{"word":"me","start":46.12,"end":46.22,"spoken":true},{"word":"higher","start":46.23,"end":46.33,"spoken":true},{"word":"and","start":46.34,"end":46.44},{"word":"higher","start":46.45,"end":46.55}],"end":46.55},{"time":49.99,"text":"Te deseo, cariño, boy it's you I desire","words":[{"word":"Te","start":49.99,"end":50.09},{"word":"deseo,","start":50.1,"end":50.2},{"word":"cariño,","start":50.21,"end":50.31},{"word":"boy","start":50.32,"end":50.42},{"word":"it's","start":50.43,"end":50.53,"spoken":true},{"word":"you","start":50.54,"end":50.64,"spoken":true},{"word":"I","start":50.65,"end":50.75,"spoken":true},{"word":"desire","start":50.76,"end":50.86,"spoken":true}],"end":50.86},{"time":51.97,"text":"Down on","words":[{"word":"Down","start":51.97,"end":52.12},{"word":"on","start":52.17,"end":52.35,"spoken":true}],"end":52.35},{"time":54.79,"text":"Your love, your love, your love","words":[{"word":"Your","start":54.79,"end":54.89},{"word":"love,","start":54.9,"end":55},{"word":"your","start":55.01,"end":55.11},{"word":"love,","start":55.12,"end":55.22},{"word":"your","start":55.23,"end":55.33},{"word":"love","start":55.34,"end":55.44}],"end":55.44},{"time":61.13,"text":"I can see my baby swingin'","words":[{"word":"I","start":61.13,"end":61.23,"spoken":true},{"word":"can","start":61.24,"end":61.34,"spoken":true},{"word":"see","start":61.35,"end":61.45,"spoken":true},{"word":"my","start":61.46,"end":61.56,"spoken":true},{"word":"baby","start":61.57,"end":61.67,"spoken":true},{"word":"swingin'","start":61.68,"end":61.78,"spoken":true}],"end":61.78},{"time":65.4,"text":"His Parliament's on fire and his hands are up","words":[{"word":"His","start":65.4,"end":65.5,"spoken":true},{"word":"Parliament's","start":65.51,"end":65.61,"spoken":true},{"word":"on","start":65.62,"end":65.72,"spoken":true},{"word":"fire","start":65.73,"end":65.83,"sung":true},{"word":"and","start":65.84,"end":65.94,"spoken":true},{"word":"his","start":65.95,"end":66.05,"spoken":true},{"word":"hands","start":66.06,"end":66.16},{"word":"are","start":66.17,"end":66.27,"spoken":true},{"word":"up","start":66.28,"end":66.38,"spoken":true}],"end":66.38},{"time":70.36,"text":"On the balcony and I'm singing","words":[{"word":"On","start":70.36,"end":70.46,"spoken":true},{"word":"the","start":70.47,"end":70.57,"sung":true},{"word":"balcony","start":70.58,"end":70.68,"spoken":true},{"word":"and","start":70.69,"end":70.79,"spoken":true},{"word":"I'm","start":70.8,"end":70.9,"spoken":true},{"word":"singing","start":70.91,"end":71.01,"spoken":true}],"end":71.01},{"time":73.69,"text":"Ooh baby, Ooh baby, I'm in love","words":[{"word":"Ooh","start":73.69,"end":73.79,"spoken":true},{"word":"baby,","start":73.8,"end":73.9,"spoken":true},{"word":"Ooh","start":73.91,"end":74.01,"spoken":true},{"word":"baby,","start":74.02,"end":74.12,"spoken":true},{"word":"I'm","start":74.13,"end":74.23},{"word":"in","start":74.24,"end":74.34},{"word":"love","start":74.35,"end":74.45}],"end":74.45},{"time":76.03,"text":"the","words":[{"word":"the","start":76.03,"end":76.39}],"end":76.39},{"time":79.38,"text":"I can see my sweet boy swayin'","words":[{"word":"I","start":79.38,"end":79.48,"spoken":true},{"word":"can","start":79.49,"end":79.59},{"word":"see","start":79.6,"end":79.7,"spoken":true},{"word":"my","start":79.71,"end":79.81,"spoken":true},{"word":"sweet","start":79.82,"end":79.92,"spoken":true},{"word":"boy","start":79.93,"end":80.03,"spoken":true},{"word":"swayin'","start":80.04,"end":80.14}],"end":80.14},{"time":83.79,"text":"He's crazy y Cubano como yo, my love","words":[{"word":"He's","start":83.79,"end":83.89,"spoken":true},{"word":"crazy","start":83.9,"end":84,"spoken":true},{"word":"y","start":84.01,"end":84.11,"spoken":true},{"word":"Cubano","start":84.12,"end":84.22,"spoken":true},{"word":"como","start":84.23,"end":84.33,"sung":true},{"word":"yo,","start":84.34,"end":84.44,"spoken":true},{"word":"my","start":84.45,"end":84.55,"spoken":true},{"word":"love","start":84.56,"end":84.66,"spoken":true}],"end":84.66},{"time":88.64,"text":"On the balcony and I'm saying","words":[{"word":"On","start":88.64,"end":88.74,"spoken":true},{"word":"the","start":88.75,"end":88.85,"spoken":true},{"word":"balcony","start":88.86,"end":88.96,"spoken":true},{"word":"and","start":88.97,"end":89.07,"spoken":true},{"word":"I'm","start":89.08,"end":89.18,"spoken":true},{"word":"saying","start":89.19,"end":89.29,"spoken":true}],"end":89.29},{"time":92.4,"text":"Move baby, move baby, I'm in love","words":[{"word":"Move","start":92.4,"end":92.5,"spoken":true},{"word":"baby,","start":92.51,"end":92.61,"spoken":true},{"word":"move","start":92.62,"end":92.72,"spoken":true},{"word":"baby,","start":92.73,"end":92.83,"spoken":true},{"word":"I'm","start":92.84,"end":92.94,"spoken":true},{"word":"in","start":92.95,"end":93.05,"spoken":true},{"word":"love","start":93.06,"end":93.16,"spoken":true}],"end":93.16},{"time":106.6,"text":"Down on the West Coast, they got their icons","words":[{"word":"Down","start":106.6,"end":106.7},{"word":"on","start":106.71,"end":106.81},{"word":"the","start":106.82,"end":106.92},{"word":"West","start":106.93,"end":107.03},{"word":"Coast,","start":107.04,"end":107.14},{"word":"they","start":107.15,"end":107.25},{"word":"got","start":107.26,"end":107.36},{"word":"their","start":107.37,"end":107.47},{"word":"icons","start":107.48,"end":107.58}],"end":107.58},{"time":110.93,"text":"Their silver starlets, their Queens of Saigons","words":[{"word":"Their","start":110.93,"end":111.03},{"word":"silver","start":111.04,"end":111.14},{"word":"starlets,","start":111.15,"end":111.25,"spoken":true},{"word":"their","start":111.26,"end":111.36,"spoken":true},{"word":"Queens","start":111.37,"end":111.47,"spoken":true},{"word":"of","start":111.48,"end":111.58,"spoken":true},{"word":"Saigons","start":111.59,"end":111.69,"spoken":true}],"end":111.69},{"time":112.67,"text":"West Coast, they got a","words":[{"word":"West","start":112.67,"end":113.19,"sung":true},{"word":"Coast,","start":113.2,"end":113.71},{"word":"they","start":113.72,"end":114.23},{"word":"got","start":114.24,"end":114.55,"sung":true},{"word":"a","start":114.65,"end":114.91,"sung":true}],"end":114.91},{"time":114.95,"text":"But you've got the music","words":[{"word":"But","start":114.95,"end":115.05},{"word":"you've","start":115.06,"end":115.16},{"word":"got","start":115.17,"end":115.27},{"word":"the","start":115.28,"end":115.38},{"word":"music","start":115.39,"end":115.49}],"end":115.49},{"time":117.4,"text":"You've got the music in you, don't you?","words":[{"word":"You've","start":117.4,"end":117.5},{"word":"got","start":117.51,"end":117.61},{"word":"the","start":117.62,"end":117.72},{"word":"music","start":117.73,"end":117.83},{"word":"in","start":117.84,"end":117.94},{"word":"you,","start":117.95,"end":118.05},{"word":"don't","start":118.06,"end":118.16},{"word":"you?","start":118.17,"end":118.27}],"end":118.27},{"time":123.82,"text":"You pull me close, I push away... I'm feeling hot to the touch","words":[{"word":"You","start":123.82,"end":123.92,"spoken":true},{"word":"pull","start":123.93,"end":124.03,"spoken":true},{"word":"me","start":124.04,"end":124.14,"spoken":true},{"word":"close,","start":124.15,"end":124.25,"spoken":true},{"word":"I","start":124.26,"end":124.36,"spoken":true},{"word":"push","start":124.37,"end":124.47},{"word":"away...","start":124.48,"end":124.58},{"word":"I'm","start":124.59,"end":124.69},{"word":"feeling","start":124.7,"end":124.8},{"word":"hot","start":124.81,"end":124.91},{"word":"to","start":124.92,"end":125.02,"sung":true},{"word":"the","start":125.03,"end":125.13,"spoken":true},{"word":"touch","start":125.14,"end":125.24,"spoken":true}],"end":125.24},{"time":128.25,"text":"You say you miss me and I wanna say I miss you so much","words":[{"word":"You","start":128.25,"end":128.35,"spoken":true},{"word":"say","start":128.36,"end":128.46,"spoken":true},{"word":"you","start":128.47,"end":128.57,"spoken":true},{"word":"miss","start":128.58,"end":128.68,"spoken":true},{"word":"me","start":128.69,"end":128.79},{"word":"and","start":128.8,"end":128.9},{"word":"I","start":128.91,"end":129.01},{"word":"wanna","start":129.02,"end":129.12,"spoken":true},{"word":"say","start":129.13,"end":129.23,"spoken":true},{"word":"I","start":129.24,"end":129.34,"spoken":true},{"word":"miss","start":129.35,"end":129.45},{"word":"you","start":129.46,"end":129.56,"spoken":true},{"word":"so","start":129.57,"end":129.67,"spoken":true},{"word":"much","start":129.68,"end":129.78,"spoken":true}],"end":129.78},{"time":132.82,"text":"But something keeps me really quiet","words":[{"word":"But","start":132.82,"end":132.92},{"word":"something","start":132.93,"end":133.03},{"word":"keeps","start":133.04,"end":133.14},{"word":"me","start":133.15,"end":133.25},{"word":"really","start":133.26,"end":133.36},{"word":"quiet","start":133.37,"end":133.47}],"end":133.47},{"time":135.56,"text":"I'm alive, I'm a lush","words":[{"word":"I'm","start":135.56,"end":135.66,"spoken":true},{"word":"alive,","start":135.67,"end":135.77,"spoken":true},{"word":"I'm","start":135.78,"end":135.88,"spoken":true},{"word":"a","start":135.89,"end":135.99},{"word":"lush","start":136,"end":136.1}],"end":136.1},{"time":136.07,"text":"sayin'","words":[{"word":"sayin'","start":136.07,"end":136.17}],"end":136.17},{"time":137.8,"text":"Hold me close you say, hush baby hush","words":[{"word":"Hold","start":137.8,"end":137.9,"spoken":true},{"word":"me","start":137.91,"end":138.01,"spoken":true},{"word":"close","start":138.02,"end":138.12,"spoken":true},{"word":"you","start":138.13,"end":138.23},{"word":"say,","start":138.24,"end":138.34,"spoken":true},{"word":"hush","start":138.35,"end":138.45,"spoken":true},{"word":"baby","start":138.46,"end":138.56,"sung":true},{"word":"hush","start":138.57,"end":138.67,"spoken":true}],"end":138.67},{"time":143.99,"text":"I can see my baby swingin'","words":[{"word":"I","start":143.99,"end":144.09,"spoken":true},{"word":"can","start":144.1,"end":144.2,"spoken":true},{"word":"see","start":144.21,"end":144.31,"spoken":true},{"word":"my","start":144.32,"end":144.42,"spoken":true},{"word":"baby","start":144.43,"end":144.53,"spoken":true},{"word":"swingin'","start":144.54,"end":144.64,"spoken":true}],"end":144.64},{"time":148.55,"text":"His Parliament's on fire and his hands are up","words":[{"word":"His","start":148.55,"end":148.65},{"word":"Parliament's","start":148.66,"end":148.76,"spoken":true},{"word":"on","start":148.77,"end":148.87,"spoken":true},{"word":"fire","start":148.88,"end":148.98,"spoken":true},{"word":"and","start":148.99,"end":149.09,"spoken":true},{"word":"his","start":149.1,"end":149.2,"spoken":true},{"word":"hands","start":149.21,"end":149.31},{"word":"are","start":149.32,"end":149.42},{"word":"up","start":149.43,"end":149.53}],"end":149.53},{"time":153.48,"text":"On the balcony and I'm singing","words":[{"word":"On","start":153.48,"end":153.58,"sung":true},{"word":"the","start":153.59,"end":153.69,"spoken":true},{"word":"balcony","start":153.7,"end":153.8,"spoken":true},{"word":"and","start":153.81,"end":153.91,"spoken":true},{"word":"I'm","start":153.92,"end":154.02,"spoken":true},{"word":"singing","start":154.03,"end":154.13,"spoken":true}],"end":154.13},{"time":156.99,"text":"Ooh baby, Ooh baby, I'm in love","words":[{"word":"Ooh","start":156.99,"end":157.09},{"word":"baby,","start":157.1,"end":157.2},{"word":"Ooh","start":157.21,"end":157.31},{"word":"baby,","start":157.32,"end":157.42,"spoken":true},{"word":"I'm","start":157.43,"end":157.53,"spoken":true},{"word":"in","start":157.54,"end":157.64,"spoken":true},{"word":"love","start":157.65,"end":157.75,"spoken":true}],"end":157.75},{"time":162.75,"text":"I can see my sweet boy swayin'","words":[{"word":"I","start":162.75,"end":162.85,"spoken":true},{"word":"can","start":162.86,"end":162.96,"spoken":true},{"word":"see","start":162.97,"end":163.07,"spoken":true},{"word":"my","start":163.08,"end":163.18,"spoken":true},{"word":"sweet","start":163.19,"end":163.29,"spoken":true},{"word":"boy","start":163.3,"end":163.4,"spoken":true},{"word":"swayin'","start":163.41,"end":163.51,"spoken":true}],"end":163.51},{"time":166.94,"text":"He's crazy y Cubano como yo, my love","words":[{"word":"He's","start":166.94,"end":167.04},{"word":"crazy","start":167.05,"end":167.15},{"word":"y","start":167.16,"end":167.26},{"word":"Cubano","start":167.27,"end":167.37,"spoken":true},{"word":"como","start":167.38,"end":167.48,"spoken":true},{"word":"yo,","start":167.49,"end":167.59},{"word":"my","start":167.6,"end":167.7,"spoken":true},{"word":"love","start":167.71,"end":167.81,"spoken":true}],"end":167.81},{"time":171.94,"text":"On the balcony and I'm saying","words":[{"word":"On","start":171.94,"end":172.04,"sung":true},{"word":"the","start":172.05,"end":172.15,"spoken":true},{"word":"balcony","start":172.16,"end":172.26,"spoken":true},{"word":"and","start":172.27,"end":172.37,"spoken":true},{"word":"I'm","start":172.38,"end":172.48,"spoken":true},{"word":"saying","start":172.49,"end":172.59,"spoken":true}],"end":172.59},{"time":175.34,"text":"Move baby, move baby, I'm in love","words":[{"word":"Move","start":175.34,"end":175.44},{"word":"baby,","start":175.45,"end":175.55,"spoken":true},{"word":"move","start":175.56,"end":175.66,"spoken":true},{"word":"baby,","start":175.67,"end":175.77,"spoken":true},{"word":"I'm","start":175.78,"end":175.88,"spoken":true},{"word":"in","start":175.89,"end":175.99,"spoken":true},{"word":"love","start":176,"end":176.1,"spoken":true}],"end":176.1},{"time":181.14,"text":"I can see my baby swingin'","words":[{"word":"I","start":181.14,"end":181.24,"spoken":true},{"word":"can","start":181.25,"end":181.35,"spoken":true},{"word":"see","start":181.36,"end":181.46},{"word":"my","start":181.47,"end":181.57,"spoken":true},{"word":"baby","start":181.58,"end":181.68,"spoken":true},{"word":"swingin'","start":181.69,"end":181.79,"spoken":true}],"end":181.79},{"time":185.68,"text":"His Parliament's on fire and his hands are up","words":[{"word":"His","start":185.68,"end":185.78},{"word":"Parliament's","start":185.79,"end":185.89},{"word":"on","start":185.9,"end":186},{"word":"fire","start":186.01,"end":186.11,"spoken":true},{"word":"and","start":186.12,"end":186.22,"spoken":true},{"word":"his","start":186.23,"end":186.33,"spoken":true},{"word":"hands","start":186.34,"end":186.44,"spoken":true},{"word":"are","start":186.45,"end":186.55,"spoken":true},{"word":"up","start":186.56,"end":186.66,"spoken":true}],"end":186.66},{"time":190.44,"text":"On the balcony and I'm singing","words":[{"word":"On","start":190.44,"end":190.54,"whisper":true},{"word":"the","start":190.55,"end":190.65},{"word":"balcony","start":190.66,"end":190.76,"spoken":true},{"word":"and","start":190.77,"end":190.87,"spoken":true},{"word":"I'm","start":190.88,"end":190.98,"spoken":true},{"word":"singing","start":190.99,"end":191.09,"spoken":true}],"end":191.09},{"time":193.91,"text":"Ooh baby, Ooh baby, I'm in love","words":[{"word":"Ooh","start":193.91,"end":194.01},{"word":"baby,","start":194.02,"end":194.12},{"word":"Ooh","start":194.13,"end":194.23},{"word":"baby,","start":194.24,"end":194.34,"spoken":true},{"word":"I'm","start":194.35,"end":194.45,"spoken":true},{"word":"in","start":194.46,"end":194.56,"spoken":true},{"word":"love","start":194.57,"end":194.67,"spoken":true}],"end":194.67},{"time":199.57,"text":"I can see my sweet boy swayin'","words":[{"word":"I","start":199.57,"end":199.67},{"word":"can","start":199.68,"end":199.78,"spoken":true},{"word":"see","start":199.79,"end":199.89,"spoken":true},{"word":"my","start":199.9,"end":200,"spoken":true},{"word":"sweet","start":200.01,"end":200.11,"spoken":true},{"word":"boy","start":200.12,"end":200.22,"spoken":true},{"word":"swayin'","start":200.23,"end":200.33}],"end":200.33},{"time":203.82,"text":"He's crazy y Cubano como yo, my love","words":[{"word":"He's","start":203.82,"end":203.92,"spoken":true},{"word":"crazy","start":203.93,"end":204.03},{"word":"y","start":204.04,"end":204.14,"spoken":true},{"word":"Cubano","start":204.15,"end":204.25,"sung":true},{"word":"como","start":204.26,"end":204.36,"spoken":true},{"word":"yo,","start":204.37,"end":204.47,"spoken":true},{"word":"my","start":204.48,"end":204.58},{"word":"love","start":204.59,"end":204.69}],"end":204.69},{"time":208.82,"text":"On the balcony and I'm saying","words":[{"word":"On","start":208.82,"end":208.92,"spoken":true},{"word":"the","start":208.93,"end":209.03,"spoken":true},{"word":"balcony","start":209.04,"end":209.14,"spoken":true},{"word":"and","start":209.15,"end":209.25},{"word":"I'm","start":209.26,"end":209.36,"spoken":true},{"word":"saying","start":209.37,"end":209.47,"spoken":true}],"end":209.47},{"time":212.34,"text":"Move baby, move baby, I'm in love","words":[{"word":"Move","start":212.34,"end":212.44,"spoken":true},{"word":"baby,","start":212.45,"end":212.55},{"word":"move","start":212.56,"end":212.66},{"word":"baby,","start":212.67,"end":212.77,"spoken":true},{"word":"I'm","start":212.78,"end":212.88,"spoken":true},{"word":"in","start":212.89,"end":212.99,"spoken":true},{"word":"love","start":213,"end":213.1,"spoken":true}],"end":213.1},{"time":216.86,"text":"I'm in love","words":[{"word":"I'm","start":216.86,"end":216.96,"spoken":true},{"word":"in","start":216.97,"end":217.07,"spoken":true},{"word":"love","start":217.08,"end":217.18,"spoken":true}],"end":217.18},{"time":219.27,"text":"I'm in love","words":[{"word":"I'm","start":219.27,"end":219.37,"spoken":true},{"word":"in","start":219.38,"end":219.48,"spoken":true},{"word":"love","start":219.49,"end":219.59,"spoken":true}],"end":219.59},{"time":221.69,"text":"I'm in love","words":[{"word":"I'm","start":221.69,"end":221.79,"spoken":true},{"word":"in","start":221.8,"end":221.9},{"word":"love","start":221.91,"end":222.01}],"end":222.01},{"time":227.567,"text":"I'm in love,","words":[{"word":"I'm","start":227.567,"end":227.667,"whisper":true},{"word":"in","start":227.567,"end":227.667,"whisper":true},{"word":"love,","start":227.567,"end":227.667,"whisper":true}],"end":227.667},{"time":227.567,"text":"I'm in love","words":[{"word":"I'm","start":227.567,"end":227.667,"whisper":true},{"word":"in","start":227.567,"end":227.667,"whisper":true},{"word":"love","start":227.567,"end":227.667,"whisper":true}],"end":227.667},{"time":227.567,"text":"(I'm in love,","words":[{"word":"(I'm","start":227.567,"end":227.667,"adlib":true,"whisper":true},{"word":"in","start":227.567,"end":227.667,"adlib":true,"whisper":true},{"word":"love,","start":227.567,"end":227.667,"adlib":true,"whisper":true}],"end":227.667},{"time":227.567,"text":"I'm in love)","words":[{"word":"I'm","start":227.567,"end":227.667,"whisper":true},{"word":"in","start":227.567,"end":227.667,"whisper":true},{"word":"love)","start":227.567,"end":227.667,"whisper":true}],"end":227.667}]