[{"time":140.36,"text":"Share my body and my mind with you","words":[{"word":"Share","start":140.36,"end":141.11,"spoken":true},{"word":"my","start":141.11,"end":141.41,"spoken":true},{"word":"body","start":141.41,"end":142.01,"spoken":true},{"word":"and","start":142.01,"end":142.46,"spoken":true},{"word":"my","start":142.46,"end":142.76},{"word":"mind","start":142.76,"end":143.36,"spoken":true},{"word":"with","start":143.36,"end":143.96,"spoken":true},{"word":"you","start":143.96,"end":144.41,"whisper":true}],"end":144.41},{"time":144.52,"text":"That's all over now","words":[{"word":"That's","start":144.52,"end":145.42},{"word":"all","start":145.42,"end":145.87,"spoken":true},{"word":"over","start":145.87,"end":146.47,"spoken":true},{"word":"now","start":146.47,"end":146.92,"spoken":true}],"end":146.92},{"time":148.58,"text":"Did what I had to do","words":[{"word":"Did","start":148.58,"end":149.03,"whisper":true},{"word":"what","start":149.03,"end":149.63,"spoken":true},{"word":"I","start":149.63,"end":149.78,"spoken":true},{"word":"had","start":149.78,"end":150.23,"spoken":true},{"word":"to","start":150.23,"end":150.53,"sung":true},{"word":"do","start":150.53,"end":150.83,"sung":true}],"end":150.83},{"time":152.01,"text":"'Cause you're so far past me now","words":[{"word":"'Cause","start":152.01,"end":152.91,"spoken":true},{"word":"you're","start":152.91,"end":153.81,"spoken":true},{"word":"so","start":153.81,"end":154.11},{"word":"far","start":154.11,"end":154.56},{"word":"past","start":154.56,"end":155.16,"spoken":true},{"word":"me","start":155.16,"end":155.46,"spoken":true},{"word":"now","start":155.46,"end":155.91,"whisper":true}],"end":155.91},{"time":156.56,"text":"Share my body and my life with you","words":[{"word":"Share","start":156.56,"end":157.273,"sung":true},{"word":"my","start":157.273,"end":157.558,"spoken":true},{"word":"body","start":157.558,"end":158.129},{"word":"and","start":158.129,"end":158.556},{"word":"my","start":158.556,"end":158.841,"spoken":true},{"word":"life","start":158.841,"end":159.412,"spoken":true},{"word":"with","start":159.412,"end":159.982,"spoken":true},{"word":"you","start":159.982,"end":160.41,"whisper":true}],"end":160.41},{"time":161.44,"text":"That's way over now","words":[{"word":"That's","start":161.44,"end":162.34,"spoken":true},{"word":"way","start":162.34,"end":162.79,"spoken":true},{"word":"over","start":162.79,"end":163.39,"spoken":true},{"word":"now","start":163.39,"end":163.84}],"end":163.84},{"time":164.45,"text":"There's not more I can do","words":[{"word":"There's","start":164.45,"end":165.5},{"word":"not","start":165.5,"end":165.95},{"word":"more","start":165.95,"end":166.55},{"word":"I","start":166.55,"end":166.7},{"word":"can","start":166.7,"end":167.15,"spoken":true},{"word":"do","start":167.15,"end":167.45,"spoken":true}],"end":167.45},{"time":168.14,"text":"You're so famous now","words":[{"word":"You're","start":168.14,"end":169.04,"spoken":true},{"word":"so","start":169.04,"end":169.34},{"word":"famous","start":169.34,"end":170.24},{"word":"now","start":170.24,"end":170.69}],"end":170.69},{"time":171.28,"text":"Got your Bible, got your gun","words":[{"word":"Got","start":171.28,"end":171.73},{"word":"your","start":171.73,"end":172.33},{"word":"Bible,","start":172.33,"end":173.23,"spoken":true},{"word":"got","start":173.23,"end":173.68,"spoken":true},{"word":"your","start":173.68,"end":174.28,"spoken":true},{"word":"gun","start":174.28,"end":174.73,"spoken":true}],"end":174.73},{"time":178.64,"text":"And you like to party and have fun","words":[{"word":"And","start":178.64,"end":179.09,"spoken":true},{"word":"you","start":179.09,"end":179.54,"sung":true},{"word":"like","start":179.54,"end":180.14},{"word":"to","start":180.14,"end":180.44},{"word":"party","start":180.44,"end":181.19},{"word":"and","start":181.19,"end":181.64},{"word":"have","start":181.64,"end":182.24,"spoken":true},{"word":"fun","start":182.24,"end":182.69}],"end":182.69},{"time":186.62,"text":"And I like my candy and your women","words":[{"word":"And","start":186.62,"end":187.07},{"word":"I","start":187.07,"end":187.22},{"word":"like","start":187.22,"end":187.82,"sung":true},{"word":"my","start":187.82,"end":188.12},{"word":"candy","start":188.12,"end":188.87,"spoken":true},{"word":"and","start":188.87,"end":189.32,"spoken":true},{"word":"your","start":189.32,"end":189.92,"spoken":true},{"word":"women","start":189.92,"end":190.67,"spoken":true}],"end":190.67},{"time":194.72,"text":"I'm finally happy now that you're gone","words":[{"word":"I'm","start":194.72,"end":195.17,"spoken":true},{"word":"finally","start":195.17,"end":196.22},{"word":"happy","start":196.22,"end":196.97,"spoken":true},{"word":"now","start":196.97,"end":197.42,"spoken":true},{"word":"that","start":197.42,"end":198.02,"spoken":true},{"word":"you're","start":198.02,"end":198.92,"spoken":true},{"word":"gone","start":198.92,"end":199.52,"spoken":true}],"end":199.52},{"time":198.77,"text":"","type":"vocal_cue","end":203.76},{"time":204.56,"text":"Put my little red party dress on","words":[{"word":"Put","start":204.56,"end":204.903,"spoken":true},{"word":"my","start":204.903,"end":205.131},{"word":"little","start":205.131,"end":205.817},{"word":"red","start":205.817,"end":206.159},{"word":"party","start":206.159,"end":206.73},{"word":"dress","start":206.73,"end":207.302},{"word":"on","start":207.302,"end":207.53}],"end":207.53},{"time":207.53,"text":"Everybody knows that I'm the best","words":[{"word":"Everybody","start":207.53,"end":208.88,"spoken":true},{"word":"knows","start":208.88,"end":209.63,"spoken":true},{"word":"that","start":209.63,"end":210.23,"spoken":true},{"word":"I'm","start":210.23,"end":210.68,"spoken":true},{"word":"the","start":210.68,"end":211.13,"spoken":true},{"word":"best","start":211.13,"end":211.73}],"end":211.73},{"time":212.92,"text":"","type":"vocal_cue","end":219.21},{"time":219.94,"text":"Get a little bit of bourbon in ya","words":[{"word":"Get","start":219.94,"end":220.254},{"word":"a","start":220.254,"end":220.358},{"word":"little","start":220.358,"end":220.986},{"word":"bit","start":220.986,"end":221.3},{"word":"of","start":221.3,"end":221.509},{"word":"bourbon","start":221.509,"end":222.242},{"word":"in","start":222.242,"end":222.451},{"word":"ya","start":222.451,"end":222.66}],"end":222.66},{"time":222.66,"text":"Get a little bit suburban and go","words":[{"word":"Get","start":222.66,"end":223.11},{"word":"a","start":223.11,"end":223.26},{"word":"little","start":223.26,"end":224.16},{"word":"bit","start":224.16,"end":224.61,"spoken":true},{"word":"suburban","start":224.61,"end":225.81,"spoken":true},{"word":"and","start":225.81,"end":226.26,"spoken":true},{"word":"go","start":226.26,"end":226.56,"spoken":true}],"end":226.56},{"time":227.95,"text":"","type":"vocal_cue","end":233.64},{"time":234.52,"text":"Because you're young, you're wild, you're free","words":[{"word":"Because","start":234.52,"end":234.935},{"word":"you're","start":234.935,"end":235.29},{"word":"young,","start":235.29,"end":235.646},{"word":"you're","start":235.646,"end":236.001,"spoken":true},{"word":"wild,","start":236.001,"end":236.298,"spoken":true},{"word":"you're","start":236.298,"end":236.653,"spoken":true},{"word":"free","start":236.653,"end":236.89,"spoken":true}],"end":236.89},{"time":236.89,"text":"You're dancin' circles around me","words":[{"word":"You're","start":236.89,"end":237.64,"spoken":true},{"word":"dancin'","start":237.64,"end":238.515},{"word":"circles","start":238.515,"end":239.39},{"word":"around","start":239.39,"end":240.14},{"word":"me","start":240.14,"end":240.39,"spoken":true}],"end":240.39},{"time":240.82,"text":"You're fuckin' crazy","words":[{"word":"You're","start":240.82,"end":241.72},{"word":"fuckin'","start":241.72,"end":242.77},{"word":"crazy","start":242.77,"end":243.52,"spoken":true}],"end":243.52},{"time":244.15,"text":"","type":"vocal_cue","end":249.69},{"time":248.25,"text":"Oh, oh Oh, oh","words":[{"word":"Oh,","start":248.25,"end":248.7},{"word":"oh","start":248.7,"end":249,"spoken":true},{"word":"Oh,","start":249,"end":249.45,"spoken":true},{"word":"oh","start":249.45,"end":249.75}],"end":249.75},{"time":252.29,"text":"","type":"vocal_cue","end":257.22},{"time":258.16,"text":"You're crazy for me","words":[{"word":"You're","start":258.16,"end":259.06,"spoken":true},{"word":"crazy","start":259.06,"end":259.81,"spoken":true},{"word":"for","start":259.81,"end":260.26,"spoken":true},{"word":"me","start":260.26,"end":260.56,"spoken":true}],"end":260.56},{"time":259.82,"text":"","type":"vocal_cue","end":265.79},{"time":266.14,"text":"I shared my body and my mind with you","words":[{"word":"I","start":266.14,"end":266.248,"spoken":true},{"word":"shared","start":266.248,"end":266.896,"spoken":true},{"word":"my","start":266.896,"end":267.111,"spoken":true},{"word":"body","start":267.111,"end":267.543},{"word":"and","start":267.543,"end":267.867,"spoken":true},{"word":"my","start":267.867,"end":268.083,"spoken":true},{"word":"mind","start":268.083,"end":268.514,"spoken":true},{"word":"with","start":268.514,"end":268.946,"spoken":true},{"word":"you","start":268.946,"end":269.27,"spoken":true}],"end":269.27},{"time":270.02,"text":"That's all over now","words":[{"word":"That's","start":270.02,"end":270.92,"spoken":true},{"word":"all","start":270.92,"end":271.37,"spoken":true},{"word":"over","start":271.37,"end":271.97,"spoken":true},{"word":"now","start":271.97,"end":272.42}],"end":272.42},{"time":273.13,"text":"I did what I had to do","words":[{"word":"I","start":273.13,"end":273.28},{"word":"did","start":273.28,"end":273.73,"spoken":true},{"word":"what","start":273.73,"end":274.33,"spoken":true},{"word":"I","start":274.33,"end":274.48,"spoken":true},{"word":"had","start":274.48,"end":274.93,"spoken":true},{"word":"to","start":274.93,"end":275.23,"spoken":true},{"word":"do","start":275.23,"end":275.53}],"end":275.53},{"time":276.5,"text":"I found another, anyhow","words":[{"word":"I","start":276.5,"end":276.65,"spoken":true},{"word":"found","start":276.65,"end":277.4,"spoken":true},{"word":"another,","start":277.4,"end":278.6,"spoken":true},{"word":"anyhow","start":278.6,"end":279.5,"sung":true}],"end":279.5},{"time":280.73,"text":"Shared my body and my mind with you","words":[{"word":"Shared","start":280.73,"end":281.63,"spoken":true},{"word":"my","start":281.63,"end":281.93,"spoken":true},{"word":"body","start":281.93,"end":282.53,"spoken":true},{"word":"and","start":282.53,"end":282.98,"spoken":true},{"word":"my","start":282.98,"end":283.28,"spoken":true},{"word":"mind","start":283.28,"end":283.88,"sung":true},{"word":"with","start":283.88,"end":284.48,"sung":true},{"word":"you","start":284.48,"end":284.93,"spoken":true}],"end":284.93},{"time":286.32,"text":"That's all over now","words":[{"word":"That's","start":286.32,"end":287.22,"spoken":true},{"word":"all","start":287.22,"end":287.67,"sung":true},{"word":"over","start":287.67,"end":288.27,"spoken":true},{"word":"now","start":288.27,"end":288.72,"spoken":true}],"end":288.72},{"time":288.94,"text":"I did what I had to do","words":[{"word":"I","start":288.94,"end":289.09,"spoken":true},{"word":"did","start":289.09,"end":289.54,"spoken":true},{"word":"what","start":289.54,"end":290.14,"spoken":true},{"word":"I","start":290.14,"end":290.29},{"word":"had","start":290.29,"end":290.74},{"word":"to","start":290.74,"end":291.04},{"word":"do","start":291.04,"end":291.34}],"end":291.34},{"time":292.52,"text":"I could see you leaving now","words":[{"word":"I","start":292.52,"end":292.667},{"word":"could","start":292.667,"end":293.401},{"word":"see","start":293.401,"end":293.841},{"word":"you","start":293.841,"end":294.282,"spoken":true},{"word":"leaving","start":294.282,"end":295.31},{"word":"now","start":295.31,"end":295.75}],"end":295.75},{"time":295.75,"text":"I got your Bible and your gun","words":[{"word":"I","start":295.75,"end":295.9},{"word":"got","start":295.9,"end":296.35},{"word":"your","start":296.35,"end":296.95},{"word":"Bible","start":296.95,"end":297.7,"spoken":true},{"word":"and","start":297.7,"end":298.15,"spoken":true},{"word":"your","start":298.15,"end":298.75},{"word":"gun","start":298.75,"end":299.2}],"end":299.2},{"time":303.56,"text":"And you love to party and have fun","words":[{"word":"And","start":303.56,"end":304.01},{"word":"you","start":304.01,"end":304.46},{"word":"love","start":304.46,"end":305.06,"spoken":true},{"word":"to","start":305.06,"end":305.36,"spoken":true},{"word":"party","start":305.36,"end":306.11,"spoken":true},{"word":"and","start":306.11,"end":306.56,"spoken":true},{"word":"have","start":306.56,"end":307.16,"spoken":true},{"word":"fun","start":307.16,"end":307.61,"spoken":true}],"end":307.61},{"time":311.98,"text":"And I love your women and all of your heroin","words":[{"word":"And","start":311.98,"end":312.43,"spoken":true},{"word":"I","start":312.43,"end":312.58},{"word":"love","start":312.58,"end":313.18},{"word":"your","start":313.18,"end":313.78,"spoken":true},{"word":"women","start":313.78,"end":314.53},{"word":"and","start":314.53,"end":314.98,"spoken":true},{"word":"all","start":314.98,"end":315.43},{"word":"of","start":315.43,"end":315.73},{"word":"your","start":315.73,"end":316.33},{"word":"heroin","start":316.33,"end":317.23}],"end":317.23},{"time":319.94,"text":"And I'm so happy now that you're gone","words":[{"word":"And","start":319.94,"end":320.39},{"word":"I'm","start":320.39,"end":320.84},{"word":"so","start":320.84,"end":321.14},{"word":"happy","start":321.14,"end":321.89,"spoken":true},{"word":"now","start":321.89,"end":322.34,"spoken":true},{"word":"that","start":322.34,"end":322.94,"spoken":true},{"word":"you're","start":322.94,"end":323.84},{"word":"gone","start":323.84,"end":324.44,"spoken":true}],"end":324.44},{"time":324.15,"text":"","type":"vocal_cue","end":329.56},{"time":330.06,"text":"Put my little red party dress on","words":[{"word":"Put","start":330.06,"end":330.467,"spoken":true},{"word":"my","start":330.467,"end":330.739},{"word":"little","start":330.739,"end":331.553},{"word":"red","start":331.553,"end":331.961},{"word":"party","start":331.961,"end":332.64},{"word":"dress","start":332.64,"end":333.318,"spoken":true},{"word":"on","start":333.318,"end":333.59}],"end":333.59},{"time":333.59,"text":"Everybody knows that I'm a mess I'm crazy, yeah, yeah","words":[{"word":"Everybody","start":333.59,"end":334.94,"spoken":true},{"word":"knows","start":334.94,"end":335.69,"spoken":true},{"word":"that","start":335.69,"end":336.29,"spoken":true},{"word":"I'm","start":336.29,"end":336.74,"spoken":true},{"word":"a","start":336.74,"end":336.89},{"word":"mess","start":336.89,"end":337.49,"spoken":true},{"word":"I'm","start":337.49,"end":337.94,"spoken":true},{"word":"crazy,","start":337.94,"end":338.84,"spoken":true},{"word":"yeah,","start":338.84,"end":339.59,"spoken":true},{"word":"yeah","start":339.59,"end":340.19,"spoken":true}],"end":340.19},{"time":340.25,"text":"","type":"vocal_cue","end":345.66},{"time":344.98,"text":"Get a little bit of bourbon in ya","words":[{"word":"Get","start":344.98,"end":345.4,"spoken":true},{"word":"a","start":345.4,"end":345.54,"spoken":true},{"word":"little","start":345.54,"end":346.38,"spoken":true},{"word":"bit","start":346.38,"end":346.8,"spoken":true},{"word":"of","start":346.8,"end":347.08,"spoken":true},{"word":"bourbon","start":347.08,"end":348.06,"spoken":true},{"word":"in","start":348.06,"end":348.34},{"word":"ya","start":348.34,"end":348.62}],"end":348.62},{"time":351.2,"text":"Go a little bit suburban and go Crazy, yeah, yeah","words":[{"word":"Go","start":351.2,"end":351.5},{"word":"a","start":351.5,"end":351.65},{"word":"little","start":351.65,"end":352.55},{"word":"bit","start":352.55,"end":353},{"word":"suburban","start":353,"end":354.2,"spoken":true},{"word":"and","start":354.2,"end":354.65,"spoken":true},{"word":"go","start":354.65,"end":354.95,"spoken":true},{"word":"Crazy,","start":354.95,"end":355.85,"spoken":true},{"word":"yeah,","start":355.85,"end":356.6},{"word":"yeah","start":356.6,"end":357.2}],"end":357.2},{"time":359.41,"text":"Because you're young, you're wild, you're free","words":[{"word":"Because","start":359.41,"end":360.17,"spoken":true},{"word":"you're","start":360.17,"end":360.821,"spoken":true},{"word":"young,","start":360.821,"end":361.472,"spoken":true},{"word":"you're","start":361.472,"end":362.123},{"word":"wild,","start":362.123,"end":362.665},{"word":"you're","start":362.665,"end":363.316},{"word":"free","start":363.316,"end":363.75,"spoken":true}],"end":363.75},{"time":363.75,"text":"You're dancin' circles around me","words":[{"word":"You're","start":363.75,"end":364.515},{"word":"dancin'","start":364.515,"end":365.407,"sung":true},{"word":"circles","start":365.407,"end":366.3,"spoken":true},{"word":"around","start":366.3,"end":367.065,"spoken":true},{"word":"me","start":367.065,"end":367.32,"spoken":true}],"end":367.32},{"time":367.32,"text":"You're fuckin' crazy","words":[{"word":"You're","start":367.32,"end":368.22,"spoken":true},{"word":"fuckin'","start":368.22,"end":369.27,"spoken":true},{"word":"crazy","start":369.27,"end":370.02,"sung":true}],"end":370.02},{"time":375.46,"text":"Oh, oh, oh, oh","words":[{"word":"Oh,","start":375.46,"end":375.91,"spoken":true},{"word":"oh,","start":375.91,"end":376.36,"spoken":true},{"word":"oh,","start":376.36,"end":376.81,"spoken":true},{"word":"oh","start":376.81,"end":377.11,"spoken":true}],"end":377.11},{"time":377.11,"text":"Oh, oh, oh, oh","words":[{"word":"Oh,","start":377.11,"end":377.56,"spoken":true},{"word":"oh,","start":377.56,"end":378.01,"spoken":true},{"word":"oh,","start":378.01,"end":378.46,"spoken":true},{"word":"oh","start":378.46,"end":378.76,"spoken":true}],"end":378.76},{"time":382.99,"text":"You're crazy for me","words":[{"word":"You're","start":382.99,"end":383.89},{"word":"crazy","start":383.89,"end":384.64},{"word":"for","start":384.64,"end":385.09},{"word":"me","start":385.09,"end":385.39}],"end":385.39},{"time":391.56,"text":"Got your Bible and your gun","words":[{"word":"Got","start":391.56,"end":392.01,"sung":true},{"word":"your","start":392.01,"end":392.61,"spoken":true},{"word":"Bible","start":392.61,"end":393.36,"whisper":true},{"word":"and","start":393.36,"end":393.81,"whisper":true},{"word":"your","start":393.81,"end":394.41,"whisper":true},{"word":"gun","start":394.41,"end":394.86,"whisper":true}],"end":394.86},{"time":399.3,"text":"You like your women and you like fun","words":[{"word":"You","start":399.3,"end":399.75,"whisper":true},{"word":"like","start":399.75,"end":400.013,"whisper":true},{"word":"your","start":399.913,"end":400.013,"whisper":true},{"word":"women","start":399.913,"end":400.013,"whisper":true},{"word":"and","start":399.913,"end":400.013,"whisper":true},{"word":"you","start":399.913,"end":400.013,"whisper":true},{"word":"like","start":399.913,"end":400.013,"whisper":true},{"word":"fun","start":399.913,"end":400.013,"whisper":true}],"end":400.013},{"time":399.913,"text":"I like my candy and your heroin","words":[{"word":"I","start":399.913,"end":400.013,"whisper":true},{"word":"like","start":399.913,"end":400.013,"whisper":true},{"word":"my","start":399.913,"end":400.013,"whisper":true},{"word":"candy","start":399.913,"end":400.013,"whisper":true},{"word":"and","start":399.913,"end":400.013,"whisper":true},{"word":"your","start":399.913,"end":400.013,"whisper":true},{"word":"heroin","start":399.913,"end":400.013,"whisper":true}],"end":400.013},{"time":399.913,"text":"And I'm so happy, so happy now you're gone","words":[{"word":"And","start":399.913,"end":400.013,"whisper":true},{"word":"I'm","start":399.913,"end":400.013,"whisper":true},{"word":"so","start":399.913,"end":400.013,"whisper":true},{"word":"happy,","start":399.913,"end":400.013,"whisper":true},{"word":"so","start":399.913,"end":400.013,"whisper":true},{"word":"happy","start":399.913,"end":400.013,"whisper":true},{"word":"now","start":399.913,"end":400.013,"whisper":true},{"word":"you're","start":399.913,"end":400.013,"whisper":true},{"word":"gone","start":399.913,"end":400.013,"whisper":true}],"end":400.013},{"time":399.913,"text":"Put my little red party dress on","words":[{"word":"Put","start":399.913,"end":400.013,"whisper":true},{"word":"my","start":399.913,"end":400.013,"whisper":true},{"word":"little","start":399.913,"end":400.013,"whisper":true},{"word":"red","start":399.913,"end":400.013,"whisper":true},{"word":"party","start":399.913,"end":400.013,"whisper":true},{"word":"dress","start":399.913,"end":400.013,"whisper":true},{"word":"on","start":399.913,"end":400.013,"whisper":true}],"end":400.013},{"time":399.913,"text":"Everybody knows that I'm a mess I'm crazy, yeah, yeah","words":[{"word":"Everybody","start":399.913,"end":400.013,"whisper":true},{"word":"knows","start":399.913,"end":400.013,"whisper":true},{"word":"that","start":399.913,"end":400.013,"whisper":true},{"word":"I'm","start":399.913,"end":400.013,"whisper":true},{"word":"a","start":399.913,"end":400.013,"whisper":true},{"word":"mess","start":399.913,"end":400.013,"whisper":true},{"word":"I'm","start":399.913,"end":400.013,"whisper":true},{"word":"crazy,","start":399.913,"end":400.013,"whisper":true},{"word":"yeah,","start":399.913,"end":400.013,"whisper":true},{"word":"yeah","start":399.913,"end":400.013,"whisper":true}],"end":400.013},{"time":399.913,"text":"Get a little bit of bourbon in ya","words":[{"word":"Get","start":399.913,"end":400.013,"whisper":true},{"word":"a","start":399.913,"end":400.013,"whisper":true},{"word":"little","start":399.913,"end":400.013,"whisper":true},{"word":"bit","start":399.913,"end":400.013,"whisper":true},{"word":"of","start":399.913,"end":400.013,"whisper":true},{"word":"bourbon","start":399.913,"end":400.013,"whisper":true},{"word":"in","start":399.913,"end":400.013,"whisper":true},{"word":"ya","start":399.913,"end":400.013,"whisper":true}],"end":400.013},{"time":399.913,"text":"Get a little bit suburban and go Crazy, yeah, yeah","words":[{"word":"Get","start":399.913,"end":400.013,"whisper":true},{"word":"a","start":399.913,"end":400.013,"whisper":true},{"word":"little","start":399.913,"end":400.013,"whisper":true},{"word":"bit","start":399.913,"end":400.013,"whisper":true},{"word":"suburban","start":399.913,"end":400.013,"whisper":true},{"word":"and","start":399.913,"end":400.013,"whisper":true},{"word":"go","start":399.913,"end":400.013,"whisper":true},{"word":"Crazy,","start":399.913,"end":400.013,"whisper":true},{"word":"yeah,","start":399.913,"end":400.013,"whisper":true},{"word":"yeah","start":399.913,"end":400.013,"whisper":true}],"end":400.013},{"time":399.913,"text":"'Cause you're young, you're wild, you're free","words":[{"word":"'Cause","start":399.913,"end":400.013,"whisper":true},{"word":"you're","start":399.913,"end":400.013,"whisper":true},{"word":"young,","start":399.913,"end":400.013,"whisper":true},{"word":"you're","start":399.913,"end":400.013,"whisper":true},{"word":"wild,","start":399.913,"end":400.013,"whisper":true},{"word":"you're","start":399.913,"end":400.013,"whisper":true},{"word":"free","start":399.913,"end":400.013,"whisper":true}],"end":400.013},{"time":399.913,"text":"You're dancin' circles around me","words":[{"word":"You're","start":399.913,"end":400.013,"whisper":true},{"word":"dancin'","start":399.913,"end":400.013,"whisper":true},{"word":"circles","start":399.913,"end":400.013,"whisper":true},{"word":"around","start":399.913,"end":400.013,"whisper":true},{"word":"me","start":399.913,"end":400.013,"whisper":true}],"end":400.013},{"time":399.913,"text":"You're fuckin' crazy","words":[{"word":"You're","start":399.913,"end":400.013,"whisper":true},{"word":"fuckin'","start":399.913,"end":400.013,"whisper":true},{"word":"crazy","start":399.913,"end":400.013,"whisper":true}],"end":400.013},{"time":399.913,"text":"Oh, oh, oh","words":[{"word":"Oh,","start":399.913,"end":400.013,"whisper":true},{"word":"oh,","start":399.913,"end":400.013,"whisper":true},{"word":"oh","start":399.913,"end":400.013,"whisper":true}],"end":400.013},{"time":399.913,"text":"Oh, oh, oh","words":[{"word":"Oh,","start":399.913,"end":400.013,"whisper":true},{"word":"oh,","start":399.913,"end":400.013,"whisper":true},{"word":"oh","start":399.913,"end":400.013,"whisper":true}],"end":400.013},{"time":399.913,"text":"You're crazy for me","words":[{"word":"You're","start":399.913,"end":400.013,"whisper":true},{"word":"crazy","start":399.913,"end":400.013,"whisper":true},{"word":"for","start":399.913,"end":400.013,"whisper":true},{"word":"me","start":399.913,"end":400.013,"whisper":true}],"end":400.013},{"time":399.913,"text":"You're crazy for me","words":[{"word":"You're","start":399.913,"end":400.013,"whisper":true},{"word":"crazy","start":399.913,"end":400.013,"whisper":true},{"word":"for","start":399.913,"end":400.013,"whisper":true},{"word":"me","start":399.913,"end":400.013,"whisper":true}],"end":400.013},{"time":400.013333,"text":"“Cruel World” is the opening track from Lana Del Rey’s 2014 album Ultraviolence."},{"time":400.013333,"text":"This track is also her personal favorite. Here’s how she described it:"},{"time":400.013333,"text":"I'm crazy, yeah, yeah"},{"time":400.013333,"text":"Crazy, yeah, yeah"},{"time":400.013333,"text":"Oh, oh"},{"time":400.013333,"text":"Oh"}]